odoo/addons/account_move_total_by_account_internal_group/README.rst
odoo/addons/account_move_total_by_account_internal_group/__init__.py
odoo/addons/account_move_total_by_account_internal_group/__manifest__.py
odoo/addons/account_move_total_by_account_internal_group/hooks.py
odoo/addons/account_move_total_by_account_internal_group/i18n/account_move_total_by_account_internal_group.pot
odoo/addons/account_move_total_by_account_internal_group/i18n/es.po
odoo/addons/account_move_total_by_account_internal_group/models/__init__.py
odoo/addons/account_move_total_by_account_internal_group/models/account_move.py
odoo/addons/account_move_total_by_account_internal_group/models/account_move_line.py
odoo/addons/account_move_total_by_account_internal_group/readme/CONTRIBUTORS.rst
odoo/addons/account_move_total_by_account_internal_group/readme/DESCRIPTION.rst
odoo/addons/account_move_total_by_account_internal_group/readme/USAGE.rst
odoo/addons/account_move_total_by_account_internal_group/static/description/icon.png
odoo/addons/account_move_total_by_account_internal_group/static/description/index.html
odoo/addons/account_move_total_by_account_internal_group/tests/__init__.py
odoo/addons/account_move_total_by_account_internal_group/tests/test_account_move_totals_by_account_internal_group.py
odoo/addons/account_move_total_by_account_internal_group/views/account_move_views.xml
odoo_addon_account_move_total_by_account_internal_group-15.0.1.0.0.4.dist-info/METADATA
odoo_addon_account_move_total_by_account_internal_group-15.0.1.0.0.4.dist-info/WHEEL
odoo_addon_account_move_total_by_account_internal_group-15.0.1.0.0.4.dist-info/top_level.txt
odoo_addon_account_move_total_by_account_internal_group-15.0.1.0.0.4.dist-info/RECORD
